simgen/__init__.py
simgen/data.py
simgen/model.py
simgen/output.py
simgen/transition.py
simgen/params/QC-age-sexe.xlsx
simgen/params/chsld_in.csv
simgen/params/chsld_out.csv
simgen/params/iso_smaf_matrix.csv
simgen/params/naissance_ed2019.xlsx
simgen/params/risk_iso.csv
simgen/params/trans_births copie.csv
simgen/params/trans_births.csv
simgen/params/trans_death_chsld.csv
simgen/params/trans_death_home.csv
simgen/params/trans_degree.csv
simgen/params/trans_divorces.csv
simgen/params/trans_iso_smaf copie.csv
simgen/params/trans_iso_smaf copie2.csv
simgen/params/trans_iso_smaf.csv
simgen/params/trans_mortality_high.csv
simgen/params/trans_mortality_low.csv
simgen/params/trans_mortality_medium.csv
simgen/params/trans_schldone.csv
simgen/params/trans_unions.csv
simgen/params/tx_em_age.csv
simgen_creei-1.0.0.dist-info/LICENSE
simgen_creei-1.0.0.dist-info/METADATA
simgen_creei-1.0.0.dist-info/WHEEL
simgen_creei-1.0.0.dist-info/top_level.txt
simgen_creei-1.0.0.dist-info/RECORD
