Metadata-Version: 2.1
Name: simgen-creei
Version: 1.0.0
Summary: Modele de microsimulation SimGen
Home-page: https://creei-models.github.io/simgen
Author: Équipe CREEi
Author-email: yann.decarie@hec.ca
License: UNKNOWN
Platform: UNKNOWN
Classifier: Programming Language :: Python :: 3
Classifier: License :: OSI Approved :: MIT License
Classifier: Operating System :: OS Independent
Requires-Python: >=3.6
Requires-Dist: pandas
Requires-Dist: numpy
Requires-Dist: numba
